crosci/fEI.h
crosci/run_DFA.c
crosci/run_fEI.pyx
crosci/dfa.h
crosci/__init__.py
crosci/run_DFA.pyx
crosci/run_fEI.c
crosci/run_fEI.cpython-311-darwin.so
crosci/fEI.c
crosci/run_DFA.cpython-311-darwin.so
crosci/outliers.py
crosci/biomarkers.py
crosci/dfa.c
crosci/.dylibs/libomp.dylib
crosci-0.1.9.dist-info/RECORD
crosci-0.1.9.dist-info/WHEEL
crosci-0.1.9.dist-info/top_level.txt
crosci-0.1.9.dist-info/METADATA
crosci-0.1.9.dist-info/licenses/LICENSE.txt
