Metadata-Version: 2.4
Name: crosci
Version: 0.1.9
Summary: Biomarkers of Critical Oscillations
Author-email: Richard Hardstone <richard.hardstone@gmail.com>, Arthur-Ervin Avramiea <a.e.avramiea@vu.nl>, Marina Diachenko <dsgvmarina@gmail.com>, Emre Cebi <emre@cebi.io>
Maintainer-email: Arthur-Ervin Avramiea <a.e.avramiea@vu.nl>, Emre Cebi <emre@cebi.io>
License-Expression: LicenseRef-AcademicPublic
Project-URL: Homepage, https://github.com/Critical-Brain-Dynamics/crosci
Classifier: Programming Language :: Python :: 3
Classifier: Development Status :: 4 - Beta
Classifier: Intended Audience :: Science/Research
Classifier: Operating System :: MacOS
Classifier: Operating System :: Microsoft :: Windows
Classifier: Operating System :: POSIX :: Linux
Classifier: Programming Language :: Cython
Classifier: Programming Language :: C
Classifier: Topic :: Scientific/Engineering
Requires-Python: >=3.11
License-File: LICENSE.txt
Requires-Dist: cython
Requires-Dist: joblib
Requires-Dist: mne
Requires-Dist: numpy
Requires-Dist: scipy
Dynamic: license-file
